<?xml version="1.0" encoding="utf-8"?>
<Corpses>
  <Corpse identifier="eahi_captaincorpse1" spawnposition="wreck" job="captain" commonness="0.5" minmoney="50" maxmoney="100">
    <!-- 舰长vip，手炮 -->
    <ItemSet commonness="1">
      <Item identifier="idcardwreck" equip="true" tags="wreck_captain" />
      <Item identifier="vipclothes1" equip="true" />
      <Item identifier="headset" equip="true" />
      <Item identifier="handcannon" equip="false">
        <Item identifier="handcannonround" />
      </Item>
    </ItemSet>
    <!-- 舰长vip，双左轮 -->
    <ItemSet commonness="1">
      <Item identifier="idcardwreck" equip="true" tags="wreck_captain" />
      <Item identifier="vipclothes1" equip="true" />
      <Item identifier="headset" equip="true" />
      <Item identifier="revolver" equip="false">
        <Item identifier="revolverround" />
        <Item identifier="revolverround" />
        <Item identifier="revolverround" />
      </Item>
      <Item identifier="revolver" equip="false">
        <Item identifier="revolverround" />
        <Item identifier="revolverround" />
        <Item identifier="revolverround" />
      </Item>
    </ItemSet>
    <!-- 海军上将制服，迅猛龙套装，双刀 -->
    <ItemSet commonness="1">
      <Item identifier="idcardwreck" equip="true" tags="wreck_captain" />
      <Item identifier="mudraptorshell_head" equip="true" />
      <Item identifier="captainsuniform3" equip="true" />
      <Item identifier="mudraptorshell" equip="true" />
      <Item identifier="headset" equip="true" />
      <Item identifier="Wf_Admiral_Katana" equip="false" />
      <Item identifier="Wf_Admiral_Wakizashi" equip="false" />
      <Item identifier="harmonica" equip="false" />
    </ItemSet>
  </Corpse>
  <Corpse identifier="eahi_engineercorpse1" spawnposition="wreck" job="engineer" commonness="1" minmoney="10" maxmoney="50">
    <!-- eahi pucs，但是里面装了焊接燃料 -->
    <ItemSet commonness="1">
      <Item identifier="idcardwreck" equip="true" tags="wreck_engineer" />
      <Item identifier="toolbelt">
        <Item identifier="screwdriver" />
        <Item identifier="wrench" />
        <Item identifier="fuelrod" />
      </Item>
      <Item identifier="EAHI_pucs">
        <Item identifier="weldingfueltank" />
      </Item>
      <Item identifier="orangejumpsuit1" equip="true" />
      <Item identifier="headset" equip="true" />
    </ItemSet>
    <!-- 背着载货助推器 -->
    <ItemSet commonness="1">
      <Item identifier="idcardwreck" equip="true" tags="wreck_engineer" />
      <Item identifier="screwdriver" equip="true" />
      <Item identifier="cargoscooter">
        <Item identifier="batterycell" />
      </Item>
      <Item identifier="orangejumpsuit2" equip="true" />
      <Item identifier="headset" equip="true" />
    </ItemSet>
  </Corpse>
  <Corpse identifier="eahi_officercorpse1" spawnposition="wreck" job="securityofficer" commonness="0.5" minmoney="10" maxmoney="50">
    <!-- 拿着EAHI高级声呐的炮手，戴防弹头盔，带热成像 -->
    <ItemSet commonness="1">
      <Item identifier="idcardwreck" equip="true" tags="wreck_security" />
      <Item identifier="ballistichelmet3" equip="true">
        <Item identifier="thermalgoggles" />
      </Item>
      <Item identifier="securityuniform2" equip="true" />
      <Item identifier="EAHI_handheldsonar" equip="false">
        <Item identifier="batterycell" />
      </Item>
      <Item identifier="bandolier" equip="true">
        <Item identifier="batterycell" />
      </Item>
      <Item identifier="headset" equip="true" />
    </ItemSet>
    <!-- 战斗VIP，海盗甲，双自动手枪 -->
    <ItemSet commonness="1">
      <Item identifier="idcardwreck" equip="true" tags="wreck_security" />
      <Item identifier="vipclothes2" equip="true" />
      <Item identifier="piratebodyarmor" equip="false" />
      <Item identifier="machinepistol" equip="false" />
      <Item identifier="machinepistol" equip="false" />
      <Item identifier="headset" equip="true" />
    </ItemSet>
    <!-- 海盗服，海盗防弹衣，手铐 -->
    <ItemSet commonness="1">
      <Item identifier="idcardwreck" equip="true" tags="wreck_security" />
      <Item identifier="pirateclotheshard" equip="true" />
      <Item identifier="piratebodyarmor" equip="false" />
      <Item identifier="handcuffs" equip="true" />
      <Item identifier="headset" equip="true" />
    </ItemSet>
  </Corpse>
  <Corpse identifier="eahi_mediccorpse1" spawnposition="wreck" job="medicaldoctor" commonness="0.5" minmoney="10" maxmoney="50">
    <!-- 凯尔希医生，口袋里有很多钙 -->
    <ItemSet commonness="1">
      <Item identifier="idcardwreck" equip="true" tags="wreck_medic" />
      <Item identifier="Kaltsituniform" equip="true" />
      <Item identifier="calcium" />
      <Item identifier="calcium" />
      <Item identifier="calcium" />
    </ItemSet>
    <!-- 医生vip，高级针筒枪，装有毒剂，戴自注射耳机 -->
    <ItemSet commonness="1">
      <Item identifier="idcardwreck" equip="true" tags="wreck_medic" />
      <Item identifier="vipclothes3" equip="true">
        <Item identifier="antibloodloss2" />
        <Item identifier="antibleeding1" />
        <Item identifier="antidama1" />
      </Item>
      <Item identifier="advancedsyringegun">
        <Item identifier="sulphuricacidsyringe" />
        <Item identifier="sulphuricacidsyringe" />
        <Item identifier="sulphuricacidsyringe" />
      </Item>
      <Item identifier="autoinjectorheadset" equip="true" />
    </ItemSet>
    <!-- 异教徒长袍，画皮蛰针，异星血浆 -->
    <ItemSet commonness="1">
      <Item identifier="idcardwreck" equip="true" tags="wreck_medic" />
      <Item identifier="cultistrobes" equip="true" />
      <Item identifier="huskstinger" />
      <Item identifier="alienblood" />
    </ItemSet>
    <!-- 狂热者长袍，画皮卵 -->
    <ItemSet commonness="1">
      <Item identifier="idcardwreck" equip="true" tags="wreck_medic" />
      <Item identifier="zealotrobes" equip="true" />
      <Item identifier="huskeggsbasic" />
      <Item identifier="huskeggsbasic" />
      <Item identifier="huskeggsbasic" />
    </ItemSet>
  </Corpse>
  <Corpse identifier="eahi_mechaniccorpse1" spawnposition="wreck" job="mechanic" commonness="1" minmoney="10" maxmoney="50">
    <!--高级机修工，4瓶焊接燃料，安全背带，重型扳手 -->
    <ItemSet commonness="1">
      <Item identifier="idcardwreck" equip="true" tags="wreck_mechanic" />
      <Item identifier="toolbelt">
        <Item identifier="weldingfueltank" />
        <Item identifier="weldingfueltank" />
        <Item identifier="weldingfueltank" />
      </Item>
      <Item identifier="weldingtool" equip="true">
        <Item identifier="weldingfueltank" />
      </Item>
      <Item identifier="heavywrench" />
      <Item identifier="bluejumpsuit2" equip="true" />
      <Item identifier="safetyharness" equip="true" />
    </ItemSet>
    <!--高级机修工2，3钢筋，安全背带，废铁炮 -->
    <ItemSet commonness="1">
      <Item identifier="idcardwreck" equip="true" tags="wreck_mechanic" />
      <Item identifier="toolbelt">
        <Item identifier="steel" />
        <Item identifier="steel" />
        <Item identifier="steel" />
      </Item>
      <Item identifier="scrapcannon" equip="true">
        <Item identifier="batterycell" />
      </Item>
      <Item identifier="heavywrench" />
      <Item identifier="bluejumpsuit2" equip="true" />
      <Item identifier="safetyharness" equip="true" />
    </ItemSet>
    <!-- 骑士机修工，铁头盔，临时装甲，重型扳手 -->
    <ItemSet commonness="1">
      <Item identifier="idcardwreck" equip="true" tags="wreck_mechanic" />
      <Item identifier="toolbelt">
        <Item identifier="weldingfueltank" />
      </Item>
      <Item identifier="heavywrench" />
      <Item identifier="ironhelmet" equip="true" />
      <Item identifier="bluejumpsuit2" equip="true" />
      <Item identifier="makeshiftarmor" equip="true" />
    </ItemSet>
  </Corpse>
  <Corpse identifier="eahi_assistantcorpse1" spawnposition="wreck" job="assistant" commonness="2" minmoney="0" maxmoney="20">
    <!-- 毕业助手，仪式剑 -->
    <ItemSet commonness="0.5">
      <Item identifier="assistantclothes" equip="true" />
      <Item identifier="ceremonialsword" />
    </ItemSet>
    <!-- 初级助手，水手指南，物品搜寻器 -->
    <ItemSet commonness="1">
      <Item identifier="assistantclothes" equip="true" />
      <Item identifier="skillbooksailorsguide" />
      <Item identifier="handhelditemfinder" />
    </ItemSet>
    <!-- 魅魔助手，宠物迅猛龙蛋 -->
    <ItemSet commonness="0.2">
      <Item identifier="succubusmask" equip="true" />
      <Item identifier="succubussuit" equip="true" />
      <Item identifier="petraptoregg" />
      <Item identifier="antibloodloss1" />
    </ItemSet>
    <!-- 圣宣助手，双仪式剑 -->
    <ItemSet commonness="0.2">
      <!--TODO: 尸体复活，加画皮免疫水压-->
      <Item identifier="shengxuanhats" equip="true" />
      <Item identifier="shengxuanuniform" equip="true" />
      <Item identifier="ceremonialsword" />
      <Item identifier="ceremonialsword" />
    </ItemSet>
  </Corpse>
</Corpses>