<?xml version="1.0" encoding="utf-8"?>
<Items>
  <!--欧罗巴之握-->
  <Item nameidentifier="divingknifeunique" descriptionidentifier="divingknifeunique" identifier="EAHI_divingknifeunique" variantof="divingknifeunique" Tags="smallitem,weapon,gunsmith,mountableweapon,divingknifeunique">
    <PreferredContainer primary="secarmcab" secondary="armcab" />
    <PreferredContainer secondary="wrecksecarmcab,abandonedsecarmcab" spawnprobability="0" />
    <Fabricate suitablefabricators="fabricator" time="5" displayname="" requiresrecipe="false">
      <RequiredSkill identifier="weapons" level="25" />
      <RequiredItem identifier="divingknifeunique" amount="1" />
      <RequiredItem identifier="carbon" amount="1" />
      <RequiredItem identifier="carbon" amount="1" />
      <RequiredItem identifier="silicon" amount="1" />
      <RequiredItem identifier="silicon" amount="1" />
    </Fabricate>
    <InventoryIcon texture="Content/Items/InventoryIconAtlas2.png" sourcerect="448,320,64,64" origin="0.5,0.5" />
    <Sprite texture="%ModDir%/Content/Items/Weapons/weapons_new.png" sourcerect="186,183,63,16" depth="0.55" origin="0.5,0.5" />
    <Body width="65" height="15" />
    <MeleeWeapon aimpos="50,0" handle1="-10,0" holdangle="30" range="50">
    </MeleeWeapon>
  </Item>
  <!--冲锋枪-->
  <Item nameidentifier="smg" descriptionidentifier="smg" identifier="EAHI_smg" variantof="smg" tags="smallitem,weapon,gun,gunsmith,mountableweapon,smg">
    <PreferredContainer spawnprobability="0" />
    <PreferredContainer spawnprobability="0" />
    <PreferredContainer spawnprobability="0" />
    <Fabricate suitablefabricators="fabricator" time="5" displayname="" requiresrecipe="false">
      <RequiredSkill identifier="weapons" level="25" />
      <RequiredItem identifier="smg" amount="1" />
      <RequiredItem identifier="carbon" amount="1" />
      <RequiredItem identifier="carbon" amount="1" />
      <RequiredItem identifier="silicon" amount="1" />
      <RequiredItem identifier="silicon" amount="1" />
    </Fabricate>
    <InventoryIcon texture="%ModDir%/Content/Items/Weapons/weapons_new.png" sourcerect="0,121,144,60" origin="0.5,0.5" />
    <Sprite texture="%ModDir%/Content/Items/Weapons/weapons_new.png" sourcerect="0,121,144,60" depth="0.55" origin="0.5,0.5" />
    <Body width="140" height="60" />
    <Holdable controlpose="true" holdpos="40,-10" aimpos="45,-10" handle1="-30,-15" handle2="26,5" holdangle="-35"/>
    <RangedWeapon>
      <RequiredSkill identifier="weapons" level="25" />
    </RangedWeapon>
  </Item>
  <!--左轮-->
  <Item nameidentifier="revolver" descriptionidentifier="revolver" identifier="EAHI_revolver" variantof="revolver" tags="smallitem,weapon,gun,pistolitem,gunsmith,mountableweapon,revolver">
    <PreferredContainer spawnprobability="0" />
    <PreferredContainer spawnprobability="0" />
    <Fabricate suitablefabricators="fabricator" time="5" displayname="" requiresrecipe="false">
      <RequiredSkill identifier="weapons" level="25" />
      <RequiredItem identifier="revolver" amount="1" />
      <RequiredItem identifier="carbon" amount="1" />
      <RequiredItem identifier="carbon" amount="1" />
      <RequiredItem identifier="silicon" amount="1" />
      <RequiredItem identifier="silicon" amount="1" />
    </Fabricate>
    <InventoryIcon texture="%ModDir%/Content/Items/Weapons/weapons_new.png" sourcerect="0,418,76,41" origin="0.5,0.5" />
    <Sprite texture="%ModDir%/Content/Items/Weapons/weapons_new.png" sourcerect="0,418,76,41" depth="0.55" origin="0.5,0.5" />
    <Body width="72" height="40" />
    <Holdable controlpose="true" aimpos="70,5" handle1="-25,-7" />
    <RangedWeapon barrelpos="29,11">
      <RequiredSkill identifier="weapons" level="25" />
    </RangedWeapon>
  </Item>
  <!--鱼叉枪-->
  <Item nameidentifier="harpoongun" descriptionidentifier="harpoongun" identifier="EAHI_harpoongun" variantof="harpoongun" tags="mediumitem,weapon,gunsmith,mountableweapon,harpoongun">
    <PreferredContainer spawnprobability="0" />
    <PreferredContainer spawnprobability="0" />
    <Sprite texture="%ModDir%/Content/Items/Weapons/weapons_new.png" sourcerect="0,203,181,39" depth="0.55" origin="0.5,0.5" />
    <Body width="180" height="30" />
    <Holdable controlpose="true" holdpos="35,-10" aimpos="45,-10" handle1="-20,-6" handle2="30,10" holdangle="-40" />
    <RangedWeapon barrelpos="85,14">
      <RequiredSkill identifier="weapons" level="25" />
    </RangedWeapon>
    <ItemContainer hideitems="true">
    </ItemContainer>
  </Item>
  <!--亡眼-->
  <Item nameidentifier="smgunique" descriptionidentifier="smgunique" identifier="EAHI_smgunique" variantof="smgunique" tags="smallitem,weapon,gun,gunsmith,mountableweapon,smgunique">
    <PreferredContainer primary="secarmcab" secondary="armcab" />
    <PreferredContainer spawnprobability="0" />
    <Fabricate suitablefabricators="fabricator" time="5" displayname="" requiresrecipe="false">
      <RequiredSkill identifier="weapons" level="25" />
      <RequiredItem identifier="smgunique" amount="1" />
      <RequiredItem identifier="carbon" amount="1" />
      <RequiredItem identifier="carbon" amount="1" />
      <RequiredItem identifier="silicon" amount="1" />
      <RequiredItem identifier="silicon" amount="1" />
    </Fabricate>
    <InventoryIcon texture="%ModDir%/Content/Items/Weapons/weapons_new.png" sourcerect="263,135,145,56" origin="0.5,0.5" />
    <Sprite texture="%ModDir%/Content/Items/Weapons/weapons_new.png" sourcerect="263,135,145,56" depth="0.55" origin="0.5,0.5" />
    <Body width="140" height="60" />
    <Holdable controlpose="true" holdpos="40,-15" aimpos="45,-10" handle1="-30,-8" handle2="18,5" holdangle="-35" />
    <RangedWeapon barrelpos="58,19">
      <RequiredSkill identifier="weapons" level="25" />
    </RangedWeapon>
  </Item>
  <!--防暴霰弹枪-->
  <Item nameidentifier="shotgun" descriptionidentifier="shotgun" identifier="EAHI_shotgun" variantof="shotgun" tags="mediumitem,weapon,gun,gunsmith,mountableweapon,shotgun">
    <PreferredContainer spawnprobability="0" />
    <PreferredContainer spawnprobability="0" />
    <PreferredContainer spawnprobability="0" />
    <PreferredContainer spawnprobability="0" />
    <Fabricate suitablefabricators="fabricator" time="5" displayname="" requiresrecipe="false">
      <RequiredSkill identifier="weapons" level="25" />
      <RequiredItem identifier="shotgun" amount="1" />
      <RequiredItem identifier="carbon" amount="1" />
      <RequiredItem identifier="carbon" amount="1" />
      <RequiredItem identifier="silicon" amount="1" />
      <RequiredItem identifier="silicon" amount="1" />
    </Fabricate>
    <InventoryIcon texture="%ModDir%/Content/Items/Weapons/weapons_new.png" sourcerect="0,65,185,54" origin="0.5,0.25" />
    <Sprite texture="%ModDir%/Content/Items/Weapons/weapons_new.png" sourcerect="0,65,185,54" depth="0.55" origin="0.5,0.25" />
    <Body width="180" height="30" />
    <Holdable controlpose="true" holdpos="40,-10" aimpos="55,5" handle1="-25,-16" handle2="26,0" holdangle="-40" />
    <RangedWeapon barrelpos="80,5">
      <RequiredSkill identifier="weapons" level="25" />
    </RangedWeapon>
  </Item>
  <!--手炮-->
  <Item nameidentifier="handcannon" descriptionidentifier="handcannon" identifier="EAHI_handcannon" variantof="handcannon" tags="smallitem,weapon,gun,gunsmith,pistolitem,mountableweapon,handcannon">
    <Fabricate suitablefabricators="fabricator" time="5" displayname="" requiresrecipe="false">
      <RequiredSkill identifier="weapons" level="25" />
      <RequiredItem identifier="handcannon" amount="1" />
      <RequiredItem identifier="carbon" amount="1" />
      <RequiredItem identifier="carbon" amount="1" />
      <RequiredItem identifier="silicon" amount="1" />
      <RequiredItem identifier="silicon" amount="1" />
    </Fabricate>    <InventoryIcon texture="%ModDir%/Content/Items/JobGear/TalentGear.png" sourcerect="303,364,42,67" origin="0.5,0.5" />
    <Sprite texture="%ModDir%/Content/Items/Jobgear/TalentGear.png" sourcerect="0,256,111,56" depth="0.55" origin="0.5,0.5" />
    <Body width="106" height="49" />
    <Holdable controlpose="true" aimpos="90,10" handle1="-45,-4" handle2="-45,-15" />
    <RangedWeapon barrelpos="40,6">
      <RequiredSkill identifier="weapons" level="25" />
    </RangedWeapon>
  </Item>
  <!--快速裂变加速器-->
  <Item nameidentifier="nucleargun" descriptionidentifier="nucleargun" identifier="EAHI_nucleargun" variantof="nucleargun" tags="mediumitem,weapon,gun,gunsmith,mountableweapon,nucleargun">
    <Fabricate suitablefabricators="fabricator" time="5" displayname="" requiresrecipe="false">
      <RequiredSkill identifier="electrical" level="25" />
      <RequiredItem identifier="nucleargun" amount="1" />
      <RequiredItem identifier="carbon" amount="1" />
      <RequiredItem identifier="carbon" amount="1" />
      <RequiredItem identifier="silicon" amount="1" />
      <RequiredItem identifier="silicon" amount="1" />
    </Fabricate>
    <Sprite texture="%ModDir%/Content/Items/JobGear/TalentGear.png" sourcerect="271,127,240,66" depth="0.55" origin="0.5,0.5" />
    <Body width="238" height="63" />
    <Wearable slots="Bag" msg="ItemMsgEquipSelect" canbeselected="false" canbepicked="true" pickkey="Select">
      <sprite name="Nuclear Gun Worn" texture="%ModDir%/Content/Items/JobGear/TalentGear.png" canbehiddenbyotherwearables="false" rotation="90" inheritlimbdepth="false" depth="0.6" sourcerect="270,127,240,66" limb="Torso" scale="0.5" origin="0.5,0.8" />
    </Wearable>
    <RangedWeapon>
      <RequiredSkill identifier="weapons" level="25" />
    </RangedWeapon>
  </Item>
  <!--自动霰弹枪-->
  <Item nameidentifier="autoshotgun" descriptionidentifier="autoshotgun" identifier="EAHI_autoshotgun" variantof="autoshotgun" tags="mediumitem,weapon,gun,gunsmith,mountableweapon,autoshotgun">
    <Fabricate suitablefabricators="fabricator" time="5" displayname="" requiresrecipe="false">
      <RequiredSkill identifier="weapons" level="25" />
      <RequiredItem identifier="autoshotgun" amount="1" />
      <RequiredItem identifier="carbon" amount="1" />
      <RequiredItem identifier="carbon" amount="1" />
      <RequiredItem identifier="silicon" amount="1" />
      <RequiredItem identifier="silicon" amount="1" />
    </Fabricate>
    <Sprite texture="%ModDir%/Content/Items/Weapons/autoshotgun_reskin.png" sourcerect="0,0,216,64" depth="0.55" origin="0.5,0.5" />
    <Body width="135" height="40" />
    <Holdable controlpose="true" holdpos="32,-30" aimpos="58,-5" handle1="-12,-20" handle2="36,-14" holdangle="-10" />
    <Wearable slots="Bag" msg="ItemMsgEquipSelect" canbeselected="false" canbepicked="true" pickkey="Select">
      <sprite name="Autoshogun Worn" texture="%ModDir%/Content/Items/Weapons/autoshotgun_reskin.png" canbehiddenbyotherwearables="false" rotation="90" inheritlimbdepth="false" depth="0.6" sourcerect="0,0,216,64" limb="Torso" ignorelimbscale="true" scale="0.62" origin="0.5,0.9" />
    </Wearable>
    <RangedWeapon barrelpos="68,10">
      <RequiredSkill identifier="weapons" level="40" />
    </RangedWeapon>
  </Item>
  <!--登船斧-->
  <Item nameidentifier="boardingaxe" descriptionidentifier="boardingaxe" identifier="EAHI_boardingaxe" variantof="boardingaxe" Tags="mediumitem,weapon,gunsmith,mountableweapon,boardingaxe">
    <Fabricate suitablefabricators="fabricator" time="5" displayname="" requiresrecipe="false">
      <RequiredSkill identifier="weapons" level="25" />
      <RequiredItem identifier="boardingaxe" amount="1" />
      <RequiredItem identifier="carbon" amount="1" />
      <RequiredItem identifier="carbon" amount="1" />
      <RequiredItem identifier="silicon" amount="1" />
      <RequiredItem identifier="silicon" amount="1" />
    </Fabricate>
    <InventoryIcon texture="%ModDir%/Content/Items/JobGear/TalentGear.png" sourcerect="165,366,64,64" origin="0.5,0.5" />
    <Sprite texture="%ModDir%/Content/Items/JobGear/TalentGear.png" sourcerect="1,425,164,53" depth="0.55" origin="0.5,0.2" />
    <Body width="161" height="20" />
  </Item>
</Items>